azure/mgmt/databoxedge/__init__.py
azure/mgmt/databoxedge/_configuration.py
azure/mgmt/databoxedge/_data_box_edge_management_client.py
azure/mgmt/databoxedge/_serialization.py
azure/mgmt/databoxedge/_version.py
azure/mgmt/databoxedge/models.py
azure/mgmt/databoxedge/py.typed
azure/mgmt/databoxedge/aio/__init__.py
azure/mgmt/databoxedge/aio/_configuration.py
azure/mgmt/databoxedge/aio/_data_box_edge_management_client.py
azure/mgmt/databoxedge/v2019_08_01/__init__.py
azure/mgmt/databoxedge/v2019_08_01/_configuration.py
azure/mgmt/databoxedge/v2019_08_01/_data_box_edge_management_client.py
azure/mgmt/databoxedge/v2019_08_01/_patch.py
azure/mgmt/databoxedge/v2019_08_01/_version.py
azure/mgmt/databoxedge/v2019_08_01/py.typed
azure/mgmt/databoxedge/v2019_08_01/aio/__init__.py
azure/mgmt/databoxedge/v2019_08_01/aio/_configuration.py
azure/mgmt/databoxedge/v2019_08_01/aio/_data_box_edge_management_client.py
azure/mgmt/databoxedge/v2019_08_01/aio/_patch.py
azure/mgmt/databoxedge/v2019_08_01/aio/operations/__init__.py
azure/mgmt/databoxedge/v2019_08_01/aio/operations/_alerts_operations.py
azure/mgmt/databoxedge/v2019_08_01/aio/operations/_bandwidth_schedules_operations.py
azure/mgmt/databoxedge/v2019_08_01/aio/operations/_containers_operations.py
azure/mgmt/databoxedge/v2019_08_01/aio/operations/_devices_operations.py
azure/mgmt/databoxedge/v2019_08_01/aio/operations/_jobs_operations.py
azure/mgmt/databoxedge/v2019_08_01/aio/operations/_nodes_operations.py
azure/mgmt/databoxedge/v2019_08_01/aio/operations/_operations.py
azure/mgmt/databoxedge/v2019_08_01/aio/operations/_operations_status_operations.py
azure/mgmt/databoxedge/v2019_08_01/aio/operations/_orders_operations.py
azure/mgmt/databoxedge/v2019_08_01/aio/operations/_patch.py
azure/mgmt/databoxedge/v2019_08_01/aio/operations/_roles_operations.py
azure/mgmt/databoxedge/v2019_08_01/aio/operations/_shares_operations.py
azure/mgmt/databoxedge/v2019_08_01/aio/operations/_skus_operations.py
azure_mgmt_databoxedge-2.0.0.dist-info/LICENSE
azure_mgmt_databoxedge-2.0.0.dist-info/METADATA
azure_mgmt_databoxedge-2.0.0.dist-info/WHEEL
azure_mgmt_databoxedge-2.0.0.dist-info/top_level.txt
azure_mgmt_databoxedge-2.0.0.dist-info/RECORD
